keyraser_client/__init__.py
keyraser_client/client.py
keyraser_client/format.py
keyraser_client/io.py
keyraser_client/test_client.py
keyraser_client/test_format.py
keyraser_client-0.5.0.dist-info/LICENSE
keyraser_client-0.5.0.dist-info/WHEEL
keyraser_client-0.5.0.dist-info/METADATA
keyraser_client-0.5.0.dist-info/RECORD
