Metadata-Version: 2.1
Name: keyraser_client
Version: 0.5.0
Summary: Python client library for the Keyraser key shredding system
Keywords: machine learning,encryption,io,network,data,privacy
Author-email: Christoph Emonds <chris+git@kant.ai>
Requires-Python: >=3.8
Classifier: Intended Audience :: Developers
Classifier: Intended Audience :: Information Technology
Classifier: Intended Audience :: Science/Research
Classifier: License :: OSI Approved :: MIT License
Classifier: Programming Language :: Python :: 3
Classifier: Topic :: Software Development :: Libraries :: Python Modules
Classifier: Topic :: Scientific/Engineering
Classifier: Topic :: Scientific/Engineering :: Artificial Intelligence
Classifier: Topic :: Scientific/Engineering :: Information Analysis
Classifier: Topic :: System :: Distributed Computing
Classifier: Topic :: System :: Logging
Requires-Dist: tox ; extra == "docs"
Requires-Dist: flit ; extra == "release"
Requires-Dist: tox ; extra == "test"
Requires-Dist: testcontainers-python ; extra == "test"
Project-URL: Documentation, https://docs.kant.ai/keyraser-client/latest/
Project-URL: Source, https://gitlab.com/kantai/keyraser/python-client/
Provides-Extra: docs
Provides-Extra: release
Provides-Extra: test
